Hamming/src/hamming_decoder_8bit.v
`include "../ecc_define.v"

module hamming_decoder_8bit (
	output reg [`HAMMING_IN_8-1:0] data_out,
	output error_flag, // if there is 1-bit error, signaling '1' otherwise '0'
	output reg correct_flag, // Singaling '1' whilst error correction is done 
	input [`HAMMING_OUT_8-1:0] data_in,
	input sys_clk,
	input rstn
);

	reg [`HAMMING_PAR_8-1:0] error_detection;
	wire [`HAMMING_IN_8-1:0] mask_byte;
	// Detect the error bit at rising edge of clock
	always @(posedge sys_clk, negedge rstn)
	begin
		if(rstn == 1'b0) 
			error_detection[`HAMMING_PAR_8-1:0] <= `HAMMING_PAR_8'd0;
		else begin
			error_detection[0] <= data_in[0] ^ data_in[0+`HAMMING_PAR_8] ^ data_in[1+`HAMMING_PAR_8] ^ data_in[3+`HAMMING_PAR_8] ^ data_in[4+`HAMMING_PAR_8] ^ data_in[6+`HAMMING_PAR_8]; 
			error_detection[1] <= data_in[1] ^ data_in[0+`HAMMING_PAR_8] ^ data_in[2+`HAMMING_PAR_8] ^ data_in[3+`HAMMING_PAR_8] ^ data_in[5+`HAMMING_PAR_8] ^ data_in[6+`HAMMING_PAR_8]; 
			error_detection[2] <= data_in[2] ^ data_in[1+`HAMMING_PAR_8] ^ data_in[2+`HAMMING_PAR_8] ^ data_in[3+`HAMMING_PAR_8];
			error_detection[3] <= data_in[3] ^ data_in[4+`HAMMING_PAR_8] ^ data_in[5+`HAMMING_PAR_8] ^ data_in[6+`HAMMING_PAR_8]; 
		end			
	end

	// Correct the error bit at falling edge of clock
	always @(negedge sys_clk, negedge rstn)
	begin
		if(rstn == 1'b0) begin 
			data_out[`HAMMING_IN_8-1:0] <= {`HAMMING_IN_8{1'bz}};
			correct_flag <= 1'b0;
		end
		else begin
			data_out[`HAMMING_IN_8-1:0] <= 	data_in[`HAMMING_OUT_8-1:`HAMMING_PAR_8] ^ mask_byte[`HAMMING_IN_8-1:0];
			correct_flag <= 1'b1;
		end
	end
	
	assign mask_byte[`HAMMING_IN_8-1:0] =  (error_detection == 'd3 ) ? 'd1   : 
					       (error_detection == 'd5 ) ? 'd2   :
					       (error_detection == 'd6 ) ? 'd4   :
					       (error_detection == 'd7 ) ? 'd8   :
					       (error_detection == 'd9 ) ? 'd16  :
					       (error_detection == 'd10) ? 'd32  :
					       (error_detection == 'd11) ? 'd64  :
					       (error_detection == 'd12) ? 'd128 : 0;

	assign error_flag = (error_detection[`HAMMING_PAR_8-1:0] == 'd0) ? 1'b0 : 1'b1;
endmodule

Hamming/src/hamming_encoder_8bit.v
`include "../ecc_define.v"

module hamming_encoder_8bit (
	input [`HAMMING_IN_8-1:0] data_in,
	output wire [`HAMMING_OUT_8-1:0] code_out
);

	wire [`HAMMING_PAR_8-1:0] parity;
	
	assign parity[0] = data_in[0] ^ data_in[1] ^ data_in[3] ^ data_in[4] ^ data_in[6];
	assign parity[1] = data_in[0] ^ data_in[2] ^ data_in[3] ^ data_in[5] ^ data_in[6];
	assign parity[2] = data_in[1] ^ data_in[2] ^ data_in[3];
	assign parity[3] = data_in[4] ^ data_in[5] ^ data_in[6]; 
	assign code_out[`HAMMING_OUT_8-1:0] = {data_in[`HAMMING_IN_8-1:0], parity[`HAMMING_PAR_8-1:0]};
endmodule

Hamming/src/hamming_tb.v
`include "../ecc_define.v"
module hamming_tb;

reg [`HAMMING_IN_8-1:0] data_in;
wire [`HAMMING_OUT_8-1:0] encoded_data;

wire [`HAMMING_IN_8-1:0] decoded_data;
wire error_flag; // if there is 1-bit error, signaling '1' otherwise '0'
wire correct_flag; // Singaling '1' whilst error correction is done 
reg sys_clk;
reg rstn;
reg [`HAMMING_IN_8-1:0] received_data;

initial begin
	$dumpfile("hamming_tb.vcd");
	$dumpvars;
	$monitor("%t: 0x%h => 0x%h | %b => %b", $time, data_in, encoded_data, data_in, encoded_data);
end

hamming_encoder_8bit u0 (
	.data_in (data_in),
	.code_out(encoded_data)
);

hamming_decoder_8bit u1 (
	.data_out     (decoded_data),
	.error_flag   (error_flag), 
	.correct_flag (correct_flag), 
	.data_in      ({received_data[`HAMMING_IN_8-1:0], encoded_data[`HAMMING_PAR_8-1:0]}),
	.sys_clk      (sys_clk),
	.rstn         (rstn)
);

initial begin
	#0 rstn <= 1'b1;
	
	repeat (5) begin
		#1 rstn <= 1'b0;
		#1 rstn <= 1'b1;
		#8;
	end
end

initial begin
	#0 sys_clk <= 1'b0;
	forever #5 sys_clk <= ~sys_clk;
end

// Simulating the 1-bit error occurance
integer bit_id; // randomly deciding one bit to be flipped
initial begin
	$srandom(`HAMMING_IN_8); // set the seed
	#0 received_data <= 'd0;
	
	repeat (5) begin
		#2 received_data <= encoded_data[`HAMMING_OUT_8-1:`HAMMING_PAR_8]; 
		//(SystemVerilog) #1 bit_id <= $urandom_range(`HAMMING_IN_8-1:0);
		#1 bit_id <= {$random} % `HAMMING_IN_8;
		#1 received_data[bit_id] <= received_data[bit_id] ^ 1'b1; // error occur
		#6; 
	end
end

initial begin
	#0  data_in <= 'h00;
	#10 data_in <= 'h0A;
	#10 data_in <= 'hFF;
	#10 data_in <= 'hA0;
	#10 data_in <= 'h1B;
	#10; $finish;
end
endmodule

Hamming/hamming_tb.vcd
$date
	Sun Aug 11 02:35:46 2019
$end

$version
	Synopsys VCS version N-2017.12-SP2_Full64
$end

$timescale
	1s
$end

$comment Csum: 1 1d60cd9487842691 $end


$scope module hamming_tb $end
$var reg 8 ! data_in [7:0] $end
$var wire 12 " encoded_data [11:0] $end
$var wire 8 # decoded_data [7:0] $end
$var wire 1 $ error_flag $end
$var wire 1 % correct_flag $end
$var reg 1 & sys_clk $end
$var reg 1 ' rstn $end
$var reg 8 ( received_data [7:0] $end
$var integer 32 ) bit_id $end

$scope module u0 $end
$var wire 8 ! data_in [7:0] $end
$var wire 12 " code_out [11:0] $end
$var wire 4 * parity [3:0] $end
$upscope $end


$scope module u1 $end
$var reg 8 # data_out [7:0] $end
$var wire 1 $ error_flag $end
$var reg 1 % correct_flag $end
$var wire 12 + data_in [11:0] $end
$var wire 1 & sys_clk $end
$var wire 1 ' rstn $end
$var reg 4 , error_detection [3:0] $end
$var wire 8 - mask_byte [7:0] $end
$upscope $end

$upscope $end

$enddefinitions $end

#0
$dumpvars
1'
0&
x$
1%
bxxxxxxxxxxxxxxxxxxxxxxxxxxxxxxxx )
b00000000 !
bxxxxxxxx #
bxxxx ,
bxxxxxxxx -
b0000 *
b00000000 (
bxxxxxxxxxxxx "
bxxxxxxxxxxxx +
$end
b00000000xxxx "
b00000000xxxx +
b000000000000 "
b000000000000 +
#1
0'
b0000 ,
0$
bzzzzzzzz #
0%
b00000000 -
#2
1'
#3
b00000000000000000000000000000100 )
#4
b00010000 (
b000100000000 +
#5
1&
b1001 ,
1$
b00010000 -
#10
b00001010 !
b000010100000 "
b000010100010 "
b000100000010 +
0&
b0010 *
b00000000 #
1%
#11
0'
b0000 ,
0$
bzzzzzzzz #
0%
b00000000 -
#12
b00001010 (
b000010100010 +
1'
#13
b00000000000000000000000000000001 )
#14
b00001000 (
b000010000010 +
#15
1&
b0101 ,
1$
b00000010 -
#20
b11111111 !
b111111110010 "
b111111111111 "
b000010001111 +
0&
b1111 *
b00001010 #
1%
#21
0'
b0000 ,
0$
bzzzzzzzz #
0%
b00000000 -
#22
b11111111 (
b111111111111 +
1'
#24
b11111101 (
b111111011111 +
#25
1&
b0101 ,
1$
b00000010 -
#30
b10100000 !
b101000001111 "
b101000001010 "
b111111011010 +
0&
b1010 *
b11111111 #
1%
#31
0'
b0000 ,
0$
bzzzzzzzz #
0%
b00000000 -
#32
b10100000 (
b101000001010 +
1'
#33
b00000000000000000000000000000011 )
#34
b10101000 (
b101010001010 +
#35
1&
b0111 ,
1$
b00001000 -
#40
b00011011 !
b000110111010 "
b000110111000 "
b101010001000 +
0&
b1000 *
b10100000 #
1%
#41
0'
b0000 ,
0$
bzzzzzzzz #
0%
b00000000 -
#42
b00011011 (
b000110111000 +
1'
#43
b00000000000000000000000000000101 )
#44
b00111011 (
b001110111000 +
#45
1&
b1010 ,
1$
b00100000 -
